shellmate/.env.example
shellmate/__init__.py
shellmate/chat_manager.py
shellmate/edit_env.py
shellmate/extractcmd.py
shellmate/shell.py
shellmate/shellmate.py
shellmate/stream_handler.py
shellmate/system_prompt.txt
shellmate/thinkinganimation.py
shmate-0.3.1.dist-info/LICENSE
shmate-0.3.1.dist-info/METADATA
shmate-0.3.1.dist-info/WHEEL
shmate-0.3.1.dist-info/entry_points.txt
shmate-0.3.1.dist-info/top_level.txt
shmate-0.3.1.dist-info/RECORD
