Metadata-Version: 2.2
Name: shmate
Version: 0.3.1
Summary: A command-line application integrating with OpenAI's API.
Author-email: David Laeer <davidlaeer@gmail.com>
Project-URL: Homepage, https://github.com/davidl09/ShellMate
License-File: LICENSE
Requires-Dist: openai
Requires-Dist: python-dotenv
